landsat9_lc/__init__.py
landsat9_lc/l9_lc_classifier.py
landsat9_lc/train_pipeline.py
landsat9_lc/models/label_encoder.json
landsat9_lc/models/pipeline_0.0.1.pkl
landsat9_lc/pipeline/__init__.py
landsat9_lc/pipeline/model_pipeline.py
landsat9_lc/pipeline/spyndex_transformer.py
landsat9_lc/processing/__init__.py
landsat9_lc/processing/data_manager.py
landsat9_lc/processing/utils.py
landsat9_lc-0.0.31.dist-info/METADATA
landsat9_lc-0.0.31.dist-info/WHEEL
landsat9_lc-0.0.31.dist-info/licenses/AUTHORS.rst
landsat9_lc-0.0.31.dist-info/licenses/LICENSE
landsat9_lc-0.0.31.dist-info/RECORD
