Metadata-Version: 2.1
Name: landsat9_lc
Version: 0.0.31
Summary: A python ML model to classify landsat 9 images
Project-URL: Homepage, https://github.com/pypa/sampleproject
Project-URL: Bug Tracker, https://github.com/pypa/sampleproject/issues
Author-email: Hector Patiño <hectorpatino24@gmail.com>
License-File: AUTHORS.rst
License-File: LICENSE
Classifier: License :: OSI Approved :: MIT License
Classifier: Operating System :: OS Independent
Classifier: Programming Language :: Python :: 3
Requires-Python: >=3.10
